README.md
setup.cfg
setup.py
cloudmersive_barcode_api_client/__init__.py
cloudmersive_barcode_api_client/api_client.py
cloudmersive_barcode_api_client/configuration.py
cloudmersive_barcode_api_client/rest.py
cloudmersive_barcode_api_client.egg-info/PKG-INFO
cloudmersive_barcode_api_client.egg-info/SOURCES.txt
cloudmersive_barcode_api_client.egg-info/dependency_links.txt
cloudmersive_barcode_api_client.egg-info/requires.txt
cloudmersive_barcode_api_client.egg-info/top_level.txt
cloudmersive_barcode_api_client/api/__init__.py
cloudmersive_barcode_api_client/api/barcode_lookup_api.py
cloudmersive_barcode_api_client/api/barcode_scan_api.py
cloudmersive_barcode_api_client/api/generate_barcode_api.py
cloudmersive_barcode_api_client/models/__init__.py
cloudmersive_barcode_api_client/models/barcode_lookup_response.py
cloudmersive_barcode_api_client/models/barcode_qr_result_item.py
cloudmersive_barcode_api_client/models/barcode_scan_qr_advanced_result.py
cloudmersive_barcode_api_client/models/barcode_scan_result.py
cloudmersive_barcode_api_client/models/product_match.py
test/__init__.py
test/test_barcode_lookup_api.py
test/test_barcode_lookup_response.py
test/test_barcode_qr_result_item.py
test/test_barcode_scan_api.py
test/test_barcode_scan_qr_advanced_result.py
test/test_barcode_scan_result.py
test/test_generate_barcode_api.py
test/test_product_match.py