Metadata-Version: 2.1
Name: cloudmersive-barcode-api-client
Version: 3.1.0
Summary: barcodeapi
Home-page: https://www.cloudmersive.com/barcode-api
Author-email: 
License: UNKNOWN
Keywords: Swagger,barcodeapi
Platform: UNKNOWN
